discord_styler/__info__.py
discord_styler/__init__.py
discord_styler/escape.py
discord_styler/py.typed
discord_styler/styler.py
discord_styled_text-1.0.0.dist-info/LICENSE
discord_styled_text-1.0.0.dist-info/METADATA
discord_styled_text-1.0.0.dist-info/WHEEL
discord_styled_text-1.0.0.dist-info/top_level.txt
discord_styled_text-1.0.0.dist-info/RECORD
