Metadata-Version: 2.1
Name: discord-styled-text
Version: 1.0.0
Summary: A small library to style text for Discord without having to remember any syntax
Home-page: https://discord-styled-text.miaow.io
Author: classabbyamp, 0x5c
Author-email: dev@kb6.ee, dev@0x5c.io
License: BSD 3-Clause
Platform: UNKNOWN
Classifier: Programming Language :: Python :: 3
Classifier: Programming Language :: Python :: 3.6
Classifier: Programming Language :: Python :: 3.7
Classifier: Programming Language :: Python :: 3.8
Classifier: Programming Language :: Python :: 3.9
Classifier: Development Status :: 5 - Production/Stable
Classifier: License :: OSI Approved :: BSD License
Classifier: Operating System :: OS Independent
Classifier: Topic :: Communications :: Chat
Classifier: Topic :: Text Processing :: Markup
Classifier: Topic :: Utilities
Classifier: Typing :: Typed
License-File: LICENSE
